gvotp/__init__.py
gvotp/gvotp.py
gvotp-0.1.1.dist-info/licenses/LICENSE
gvotp-0.1.1.dist-info/METADATA
gvotp-0.1.1.dist-info/WHEEL
gvotp-0.1.1.dist-info/top_level.txt
gvotp-0.1.1.dist-info/RECORD
