Metadata-Version: 2.4
Name: gvotp
Version: 0.1.1
Summary: A lightweight in-memory OTP generator and verifier with external record support
Author-email: Bittu Singh <bittusinghtech@gmail.com>
License-Expression: MIT
Requires-Python: >=3.7
License-File: LICENSE
Dynamic: license-file
